[
  {
    "text": "MACCFA",
    "score": 0.8298322558403015,
    "position": [
      343,
      129,
      169,
      42
    ],
    "distance": 0
  },
  {
    "text": "小抹茶館",
    "score": 0.7052622437477112,
    "position": [
      661,
      103,
      153,
      48
    ],
    "distance": 0
  },
  {
    "text": "HOUSE",
    "score": 0.8625112771987915,
    "position": [
      513,
      126,
      138,
      50
    ],
    "distance": 0
  },
  {
    "text": "32",
    "score": 0.9994230270385742,
    "position": [
      233,
      226,
      29,
      29
    ],
    "distance": 0
  },
  {
    "text": "NACCHA",
    "score": 0.9600844979286194,
    "position": [
      379,
      234,
      81,
      31
    ],
    "distance": 0
  },
  {
    "text": "新成市廣場",
    "score": 0.8347645998001099,
    "position": [
      589,
      218,
      164,
      47
    ],
    "distance": 0
  },
  {
    "text": "HOUSE",
    "score": 0.9749976396560669,
    "position": [
      464,
      235,
      68,
      31
    ],
    "distance": 0
  },
  {
    "text": "KITTV",
    "score": 0.8575900197029114,
    "position": [
      757,
      318,
      78,
      36
    ],
    "distance": 0
  },
  {
    "text": "Wednesday",
    "score": 0.9997051954269409,
    "position": [
      277,
      349,
      138,
      37
    ],
    "distance": 0
  },
  {
    "text": "14:44",
    "score": 0.9421106576919556,
    "position": [
      574,
      339,
      74,
      35
    ],
    "distance": 0
  },
  {
    "text": "July.",
    "score": 0.9500946998596191,
    "position": [
      423,
      357,
      71,
      35
    ],
    "distance": 0
  },
  {
    "text": "2015",
    "score": 0.999270498752594,
    "position": [
      498,
      350,
      61,
      36
    ],
    "distance": 0
  },
  {
    "text": "金額",
    "score": 0.9807124137878418,
    "position": [
      770,
      350,
      68,
      39
    ],
    "distance": 0
  },
  {
    "text": "菜名",
    "score": 0.7537844181060791,
    "position": [
      235,
      380,
      59,
      34
    ],
    "distance": 0
  },
  {
    "text": "單價",
    "score": 0.9691274762153625,
    "position": [
      512,
      380,
      63,
      40
    ],
    "distance": 0
  },
  {
    "text": "數量",
    "score": 0.9999068975448608,
    "position": [
      592,
      370,
      63,
      37
    ],
    "distance": 0
  },
  {
    "text": "HK$79.00",
    "score": 0.9634914398193359,
    "position": [
      744,
      420,
      130,
      47
    ],
    "distance": 0
  },
  {
    "text": "七夕素茄",
    "score": 0.7727259993553162,
    "position": [
      262,
      446,
      116,
      34
    ],
    "distance": 0
  },
  {
    "text": "079.00",
    "score": 0.9405103325843811,
    "position": [
      497,
      445,
      89,
      41
    ],
    "distance": 0
  },
  {
    "text": "00",
    "score": 0.9276918172836304,
    "position": [
      787,
      450,
      41,
      31
    ],
    "distance": 0
  },
  {
    "text": "HK$5g.",
    "score": 0.8637039065361023,
    "position": [
      727,
      456,
      92,
      37
    ],
    "distance": 0
  },
  {
    "text": "仁味香殼牛肉鳥冬",
    "score": 0.7103586196899414,
    "position": [
      317,
      482,
      224,
      32
    ],
    "distance": 0
  },
  {
    "text": "059.",
    "score": 0.8990236520767212,
    "position": [
      480,
      479,
      57,
      33
    ],
    "distance": 0
  },
  {
    "text": "100",
    "score": 0.8470728993415833,
    "position": [
      518,
      475,
      48,
      35
    ],
    "distance": 0
  },
  {
    "text": "黑麻由濃厚豬骨拉龜",
    "score": 0.855658233165741,
    "position": [
      328,
      516,
      256,
      33
    ],
    "distance": 0
  },
  {
    "text": "HK$69",
    "score": 0.9640682339668274,
    "position": [
      727,
      527,
      84,
      35
    ],
    "distance": 0
  },
  {
    "text": "00",
    "score": 0.8815973401069641,
    "position": [
      790,
      523,
      53,
      38
    ],
    "distance": 0
  },
  {
    "text": "00",
    "score": 0.968005895614624,
    "position": [
      518,
      543,
      43,
      29
    ],
    "distance": 0
  },
  {
    "text": "C69.",
    "score": 0.8218409419059753,
    "position": [
      481,
      547,
      58,
      34
    ],
    "distance": 0
  },
  {
    "text": "HK$4.00",
    "score": 0.8959367871284485,
    "position": [
      752,
      563,
      130,
      42
    ],
    "distance": 0
  },
  {
    "text": "074.00",
    "score": 0.9057520031929016,
    "position": [
      496,
      581,
      89,
      38
    ],
    "distance": 0
  },
  {
    "text": "L）古力牛加味茶",
    "score": 0.6528308391571045,
    "position": [
      317,
      620,
      248,
      30
    ],
    "distance": 0
  },
  {
    "text": "HK$39",
    "score": 0.9766453504562378,
    "position": [
      733,
      639,
      86,
      37
    ],
    "distance": 0
  },
  {
    "text": "00",
    "score": 0.8162115812301636,
    "position": [
      801,
      636,
      46,
      34
    ],
    "distance": 0
  },
  {
    "text": "039,00",
    "score": 0.9135939478874207,
    "position": [
      497,
      652,
      91,
      38
    ],
    "distance": 0
  },
  {
    "text": "山白朱古力中奶抹茶",
    "score": 0.6236498355865479,
    "position": [
      326,
      693,
      283,
      33
    ],
    "distance": 0
  },
  {
    "text": "HK$44:00",
    "score": 0.8728851675987244,
    "position": [
      763,
      716,
      141,
      44
    ],
    "distance": 0
  },
  {
    "text": "044:00",
    "score": 0.8958716988563538,
    "position": [
      497,
      726,
      95,
      41
    ],
    "distance": 0
  },
  {
    "text": "00",
    "score": 0.7859593629837036,
    "position": [
      523,
      764,
      42,
      35
    ],
    "distance": 0
  },
  {
    "text": "HK$49",
    "score": 0.8668991923332214,
    "position": [
      742,
      759,
      89,
      36
    ],
    "distance": 0
  },
  {
    "text": ".00",
    "score": 0.9400098919868469,
    "position": [
      804,
      757,
      61,
      36
    ],
    "distance": 0
  },
  {
    "text": "株大福音",
    "score": 0.6526889801025391,
    "position": [
      252,
      769,
      152,
      32
    ],
    "distance": 0
  },
  {
    "text": "049",
    "score": 0.940866231918335,
    "position": [
      475,
      766,
      48,
      33
    ],
    "distance": 0
  },
  {
    "text": "小計",
    "score": 0.9999819993972778,
    "position": [
      201,
      850,
      66,
      40
    ],
    "distance": 0
  },
  {
    "text": "HK$413.00",
    "score": 0.8927342295646667,
    "position": [
      764,
      843,
      156,
      39
    ],
    "distance": 0
  },
  {
    "text": "服務費",
    "score": 0.999775230884552,
    "position": [
      215,
      891,
      98,
      38
    ],
    "distance": 0
  },
  {
    "text": "10%",
    "score": 0.9017220139503479,
    "position": [
      583,
      887,
      47,
      34
    ],
    "distance": 0
  },
  {
    "text": "HK$41.30",
    "score": 0.9663387537002563,
    "position": [
      774,
      886,
      143,
      39
    ],
    "distance": 0
  },
  {
    "text": "合言丨",
    "score": 0.7273918986320496,
    "position": [
      226,
      931,
      127,
      41
    ],
    "distance": 0
  },
  {
    "text": "HK$454：30",
    "score": 0.8507487177848816,
    "position": [
      694,
      930,
      306,
      39
    ],
    "distance": 0
  },
  {
    "text": "客數：4",
    "score": 0.9581013321876526,
    "position": [
      220,
      974,
      123,
      37
    ],
    "distance": 0
  },
  {
    "text": "桌號：7",
    "score": 0.9990686178207397,
    "position": [
      360,
      973,
      121,
      44
    ],
    "distance": 0
  },
  {
    "text": "No",
    "score": 0.9840198755264282,
    "position": [
      644,
      974,
      36,
      34
    ],
    "distance": 0
  },
  {
    "text": "000057",
    "score": 0.8540461659431458,
    "position": [
      725,
      973,
      111,
      36
    ],
    "distance": 0
  },
  {
    "text": ":001",
    "score": 0.9977418780326843,
    "position": [
      813,
      972,
      68,
      35
    ],
    "distance": 0
  }
]