{"data_mtime":1698339076,"dep_lines":[16,34,37,40,24,28,44,1,4,11,1,1,1,1,1,8,14],"dep_prios":[5,5,5,5,5,5,5,5,5,5,5,30,30,30,30,5,10],"dependencies":["eth._utils.transactions","eth.rlp.logs","eth.rlp.receipts","eth.rlp.transactions","eth.abc","eth.constants","eth.validation","functools","typing","eth_typing","builtins","abc","eth._utils","eth.rlp","eth_typing.evm"],"hash":"2a9ec6530a55f17b4fd1e5c58e6dcfd4739dca62da7a15bd97fc4f17e7b9942d","id":"eth.vm.forks.frontier.transactions","ignore_all":true,"interface_hash":"e9b8c1128b1f308e46dbe81990698893c74a5da0ea41bfeaabe0c90042905174","mtime":1697465635,"options":{"allow_redefinition":false,"allow_untyped_globals":false,"always_false":[],"always_true":[],"bazel":false,"check_untyped_defs":false,"disable_bytearray_promotion":false,"disable_error_code":[],"disable_memoryview_promotion":false,"disabled_error_codes":[],"disallow_any_decorated":false,"disallow_any_explicit":false,"disallow_any_expr":false,"disallow_any_generics":false,"disallow_any_unimported":false,"disallow_incomplete_defs":false,"disallow_subclassing_any":false,"disallow_untyped_calls":false,"disallow_untyped_decorators":false,"disallow_untyped_defs":false,"enable_error_code":[],"enabled_error_codes":[],"extra_checks":false,"follow_imports":"normal","follow_imports_for_stubs":false,"ignore_errors":false,"ignore_missing_imports":false,"implicit_optional":false,"implicit_reexport":true,"local_partial_types":false,"mypyc":false,"new_type_inference":false,"platform":"darwin","plugins":[],"strict_concatenate":false,"strict_equality":false,"strict_optional":true,"warn_no_return":true,"warn_return_any":false,"warn_unreachable":false,"warn_unused_ignores":false},"path":"/Users/coccoinomane/web3/airfarm/.venv/lib/python3.11/site-packages/eth/vm/forks/frontier/transactions.py","plugin_data":null,"size":5952,"suppressed":["eth_keys.datatypes","rlp"],"version_id":"1.6.1"}